<annotation>
	<folder>images</folder>
	<filename>40t.jpg</filename>
	<path>/home/apiiit-rkv/Desktop/toll plaza/images/40t.jpg</path>
	<source>
		<database>Unknown</database>
	</source>
	<size>
		<width>711</width>
		<height>400</height>
		<depth>3</depth>
	</size>
	<segmented>0</segmented>
	<object>
		<name>toll plaza</name>
		<pose>Unspecified</pose>
		<truncated>0</truncated>
		<difficult>0</difficult>
		<bndbox>
			<xmin>112</xmin>
			<ymin>95</ymin>
			<xmax>611</xmax>
			<ymax>154</ymax>
		</bndbox>
	</object>
	<object>
		<name>toll plaza</name>
		<pose>Unspecified</pose>
		<truncated>0</truncated>
		<difficult>0</difficult>
		<bndbox>
			<xmin>201</xmin>
			<ymin>164</ymin>
			<xmax>524</xmax>
			<ymax>240</ymax>
		</bndbox>
	</object>
</annotation>
